aio_api_sm/__init__.py
aio_api_sm-1.3.dist-info/LICENSE.md
aio_api_sm-1.3.dist-info/METADATA
aio_api_sm-1.3.dist-info/WHEEL
aio_api_sm-1.3.dist-info/top_level.txt
aio_api_sm-1.3.dist-info/RECORD
