Metadata-Version: 2.1
Name: aio-api-sm
Version: 1.3
Summary: Asynchronous HTTP Session Manager with retry, rate limiting, and more.
Author: cbinckly
License: Copyright 2022 Chris Binckly
Project-URL: Homepage, https://github.com/cbinckly/aio-api-sm
Keywords: aio,aiohttp,session,rate,retry,request
Classifier: Programming Language :: Python :: 3
Requires-Python: >=3.9
License-File: LICENSE.md
Requires-Dist: python-dateutil
Requires-Dist: aiohttp
